{"total": {"lines":{"total":458,"covered":442,"skipped":0,"pct":96.51},"statements":{"total":539,"covered":510,"skipped":0,"pct":94.62},"functions":{"total":138,"covered":132,"skipped":0,"pct":95.65},"branches":{"total":318,"covered":260,"skipped":0,"pct":81.76}}
,"/Users/tomaspietravallo/Documents/GitHub/sparkar-volts/volts.ts": {"lines":{"total":458,"covered":442,"skipped":0,"pct":96.51},"functions":{"total":138,"covered":132,"skipped":0,"pct":95.65},"statements":{"total":539,"covered":510,"skipped":0,"pct":94.62},"branches":{"total":318,"covered":260,"skipped":0,"pct":81.76}}
}
